heroes_ai_handler/BlobConversionHandler.py
heroes_ai_handler/ChatCompletor.py
heroes_ai_handler/DatabaseHandler.py
heroes_ai_handler/EmbeddingHandler.py
heroes_ai_handler/FileHandler.py
heroes_ai_handler/Logger.py
heroes_ai_handler/Printer.py
heroes_ai_handler/Utils.py
heroes_ai_handler/WebsiteScraper.py
heroes_ai_handler/__init__.py
heroes_ai_handler-0.2.12.dist-info/METADATA
heroes_ai_handler-0.2.12.dist-info/WHEEL
heroes_ai_handler-0.2.12.dist-info/top_level.txt
heroes_ai_handler-0.2.12.dist-info/RECORD
