Metadata-Version: 2.1
Name: heroes-ai-handler
Version: 0.2.12
Summary: A package for handling GPT, embeddings, and data for an AI Assistant.
Home-page: https://pypi.org/project/heroes-ai-handler/
Author: Stefan Jansen
Author-email: stefan.jansen@heroes.nl
License: MIT
Classifier: Programming Language :: Python :: 3
Classifier: License :: OSI Approved :: MIT License
Classifier: Operating System :: OS Independent
Requires-Python: >=3.8
Requires-Dist: undetected-chromedriver
Requires-Dist: langdetect
Requires-Dist: python-docx
Requires-Dist: requests
Requires-Dist: PyMuPDF
Requires-Dist: pyodbc
Requires-Dist: weaviate-client
Requires-Dist: tiktoken
Requires-Dist: langchain
Requires-Dist: azure-storage-blob
Requires-Dist: beautifulsoup4
Requires-Dist: python-dotenv
